seisscan/__init__.py
seisscan/backprojection/__init__.py
seisscan/backprojection/backprojection.py
seisscan/backprojection/brightness.py
seisscan/backprojection/sliding_window_calculation.py
seisscan/data/evt_dict.json
seisscan/data/okl.tvel
seisscan/data/okl_wavefields-20160711-055516_allsta.p
seisscan/data/station-okl.xml
seisscan/data/subnetworks.json
seisscan/imaging/__init__.py
seisscan/imaging/waveform.py
seisscan/read_data/__init__.py
seisscan/read_data/read_example.py
seisscan/read_data/read_fdsn.py
seisscan/waveform_similarity/__init__.py
seisscan/waveform_similarity/correlation.py
seisscan/waveform_similarity/local_similarity.py
seisscan/waveform_similarity/peak_cross_correlation.py
seisscan-0.1.0.dist-info/LICENSE
seisscan-0.1.0.dist-info/METADATA
seisscan-0.1.0.dist-info/WHEEL
seisscan-0.1.0.dist-info/RECORD
