Metadata-Version: 2.1
Name: seisscan
Version: 0.1.0
Summary: A package to detect and locate microearthquakes.
License: MIT
Author: Ketan Singha Roy
Author-email: ketansingharoy@gmail.com
Requires-Python: >=3.10
Classifier: License :: OSI Approved :: MIT License
Classifier: Programming Language :: Python :: 3
Classifier: Programming Language :: Python :: 3.10
Classifier: Programming Language :: Python :: 3.11
Classifier: Programming Language :: Python :: 3.12
Requires-Dist: cartopy (>=0.23.0)
Requires-Dist: dask (>=2024.8.0)
Requires-Dist: distributed (>=2024.8.0)
Requires-Dist: nbsphinx (>=0.9.4,<0.10.0)
Requires-Dist: numpy (==1.26.4)
Requires-Dist: obspy (==1.4.0)
Requires-Dist: pandas (>=2.2.2)
Requires-Dist: pandoc (>=2.4,<3.0)
Requires-Dist: sphinx-copybutton (>=0.5.2,<0.6.0)
Requires-Dist: utm (>=0.7.0)
